[{"fiscalDateEnding": "2020-12-31", "reportedDate": "2020-12-31", "reportedEPS": "-0.6", "estimatedEPS": "-0.59", "surprise": "-0.01", "surprisePercentage": "-1.6949"}, {"fiscalDateEnding": "2020-09-30", "reportedDate": "2020-11-16", "reportedEPS": "-0.6", "estimatedEPS": "-0.5133", "surprise": "-0.0867", "surprisePercentage": "-16.8907"}, {"fiscalDateEnding": "2020-06-30", "reportedDate": "2020-09-09", "reportedEPS": "-0.56", "estimatedEPS": "-0.458", "surprise": "-0.102", "surprisePercentage": "-22.2707"}, {"fiscalDateEnding": "2020-03-31", "reportedDate": "2020-05-13", "reportedEPS": "-0.5", "estimatedEPS": "-0.54", "surprise": "0.04", "surprisePercentage": "7.4074"}, {"fiscalDateEnding": "2019-12-31", "reportedDate": "2020-02-05", "reportedEPS": "-0.47", "estimatedEPS": "-0.588", "surprise": "0.118", "surprisePercentage": "20.068"}, {"fiscalDateEnding": "2019-09-30", "reportedDate": "2019-11-12", "reportedEPS": "-0.64", "estimatedEPS": "-0.625", "surprise": "-0.015", "surprisePercentage": "-2.4"}, {"fiscalDateEnding": "2019-06-30", "reportedDate": "2019-09-26", "reportedEPS": "-0.58", "estimatedEPS": "-0.42", "surprise": "-0.16", "surprisePercentage": "-38.0952"}, {"fiscalDateEnding": "2019-03-31", "reportedDate": "2019-05-07", "reportedEPS": "0.63", "estimatedEPS": "-0.53", "surprise": "1.16", "surprisePercentage": "218.8679"}, {"fiscalDateEnding": "2018-12-31", "reportedDate": "2019-02-07", "reportedEPS": "-0.23", "estimatedEPS": "-0.7", "surprise": "0.47", "surprisePercentage": "67.1429"}, {"fiscalDateEnding": "2018-09-30", "reportedDate": "2018-11-08", "reportedEPS": "-0.4761", "estimatedEPS": "-0.48", "surprise": "0.0039", "surprisePercentage": "0.8125"}, {"fiscalDateEnding": "2018-06-30", "reportedDate": "2018-09-10", "reportedEPS": "-0.37", "estimatedEPS": "-0.325", "surprise": "-0.045", "surprisePercentage": "-13.8462"}, {"fiscalDateEnding": "2018-03-31", "reportedDate": "2018-05-08", "reportedEPS": "-0.45", "estimatedEPS": "-0.392", "surprise": "-0.058", "surprisePercentage": "-14.7959"}, {"fiscalDateEnding": "2017-12-31", "reportedDate": "2018-02-09", "reportedEPS": "-0.29", "estimatedEPS": "-0.176", "surprise": "-0.114", "surprisePercentage": "-64.7727"}, {"fiscalDateEnding": "2017-09-30", "reportedDate": "2017-11-07", "reportedEPS": "-0.08", "estimatedEPS": "-0.125", "surprise": "0.045", "surprisePercentage": "36"}, {"fiscalDateEnding": "2017-06-30", "reportedDate": "2017-09-13", "reportedEPS": "-0.18", "estimatedEPS": "-0.075", "surprise": "-0.105", "surprisePercentage": "-140"}, {"fiscalDateEnding": "2017-03-31", "reportedDate": "2017-05-10", "reportedEPS": "-0.05", "estimatedEPS": "0.0675", "surprise": "-0.1175", "surprisePercentage": "-174.0741"}, {"fiscalDateEnding": "2016-12-31", "reportedDate": "2017-02-08", "reportedEPS": "0.11", "estimatedEPS": "0.0375", "surprise": "0.0725", "surprisePercentage": "193.3333"}, {"fiscalDateEnding": "2016-09-30", "reportedDate": "2016-11-08", "reportedEPS": "0.2", "estimatedEPS": "-0.01", "surprise": "0.21", "surprisePercentage": "2100"}, {"fiscalDateEnding": "2016-06-30", "reportedDate": "2016-09-12", "reportedEPS": "0.15", "estimatedEPS": "0.0767", "surprise": "0.0733", "surprisePercentage": "95.5671"}, {"fiscalDateEnding": "2016-03-31", "reportedDate": "2016-05-09", "reportedEPS": "0.11", "estimatedEPS": "0.17", "surprise": "-0.06", "surprisePercentage": "-35.2941"}, {"fiscalDateEnding": "2015-12-31", "reportedDate": "2016-02-08", "reportedEPS": "0.17", "estimatedEPS": "-0.3425", "surprise": "0.5125", "surprisePercentage": "149.635"}, {"fiscalDateEnding": "2015-09-30", "reportedDate": "2015-11-05", "reportedEPS": "-0.53", "estimatedEPS": "-0.19", "surprise": "-0.34", "surprisePercentage": "-178.9474"}, {"fiscalDateEnding": "2015-06-30", "reportedDate": "2015-09-10", "reportedEPS": "-0.48", "estimatedEPS": "-0.4", "surprise": "-0.08", "surprisePercentage": "-20"}, {"fiscalDateEnding": "2015-03-31", "reportedDate": "2015-05-11", "reportedEPS": "-0.38", "estimatedEPS": "-0.33", "surprise": "-0.05", "surprisePercentage": "-15.1515"}, {"fiscalDateEnding": "2014-12-31", "reportedDate": "2015-02-11", "reportedEPS": "-0.28", "estimatedEPS": "-0.38", "surprise": "0.1", "surprisePercentage": "26.3158"}, {"fiscalDateEnding": "2014-09-30", "reportedDate": "2014-11-12", "reportedEPS": "-0.34", "estimatedEPS": "-0.29", "surprise": "-0.05", "surprisePercentage": "-17.2414"}, {"fiscalDateEnding": "2014-06-30", "reportedDate": "2014-09-26", "reportedEPS": "-0.32", "estimatedEPS": "-0.35", "surprise": "0.03", "surprisePercentage": "8.5714"}, {"fiscalDateEnding": "2014-03-31", "reportedDate": "2014-05-14", "reportedEPS": "-25.45", "estimatedEPS": "-0.37", "surprise": "-25.08", "surprisePercentage": "-6778.3784"}]