[{"fiscalDateEnding": "2020-09-30", "reportedDate": "2020-11-12", "reportedEPS": "-0.2336", "estimatedEPS": "None", "surprise": "None", "surprisePercentage": "None"}, {"fiscalDateEnding": "2020-06-30", "reportedDate": "2020-07-06", "reportedEPS": "-0.0588", "estimatedEPS": "None", "surprise": "None", "surprisePercentage": "None"}, {"fiscalDateEnding": "2020-03-31", "reportedDate": "2020-05-15", "reportedEPS": "-0.1642", "estimatedEPS": "None", "surprise": "None", "surprisePercentage": "None"}, {"fiscalDateEnding": "2019-12-31", "reportedDate": "2020-03-30", "reportedEPS": "-1.644", "estimatedEPS": "None", "surprise": "None", "surprisePercentage": "None"}, {"fiscalDateEnding": "2019-09-30", "reportedDate": "2019-11-14", "reportedEPS": "0.0524", "estimatedEPS": "None", "surprise": "None", "surprisePercentage": "None"}, {"fiscalDateEnding": "2019-06-30", "reportedDate": "2019-08-14", "reportedEPS": "0.0047", "estimatedEPS": "None", "surprise": "None", "surprisePercentage": "None"}, {"fiscalDateEnding": "2019-03-31", "reportedDate": "2019-05-17", "reportedEPS": "-0.1247", "estimatedEPS": "None", "surprise": "None", "surprisePercentage": "None"}, {"fiscalDateEnding": "2018-12-31", "reportedDate": "2019-03-22", "reportedEPS": "-0.46", "estimatedEPS": "None", "surprise": "None", "surprisePercentage": "None"}, {"fiscalDateEnding": "2018-09-30", "reportedDate": "2018-10-26", "reportedEPS": "-0.13", "estimatedEPS": "-0.24", "surprise": "0.11", "surprisePercentage": "45.8333"}, {"fiscalDateEnding": "2018-06-30", "reportedDate": "2018-08-08", "reportedEPS": "-0.12", "estimatedEPS": "-0.16", "surprise": "0.04", "surprisePercentage": "25"}, {"fiscalDateEnding": "2018-03-31", "reportedDate": "2018-05-10", "reportedEPS": "-0.18", "estimatedEPS": "None", "surprise": "None", "surprisePercentage": "None"}, {"fiscalDateEnding": "2017-12-31", "reportedDate": "2018-03-23", "reportedEPS": "-0.2912", "estimatedEPS": "None", "surprise": "None", "surprisePercentage": "None"}, {"fiscalDateEnding": "2017-09-30", "reportedDate": "2017-11-13", "reportedEPS": "-0.45", "estimatedEPS": "-0.18", "surprise": "-0.27", "surprisePercentage": "-150"}, {"fiscalDateEnding": "2017-06-30", "reportedDate": "2017-08-04", "reportedEPS": "-0.2", "estimatedEPS": "None", "surprise": "None", "surprisePercentage": "None"}, {"fiscalDateEnding": "2017-03-31", "reportedDate": "2017-05-12", "reportedEPS": "-0.13", "estimatedEPS": "-0.06", "surprise": "-0.07", "surprisePercentage": "-116.6667"}, {"fiscalDateEnding": "2016-12-31", "reportedDate": "2017-03-17", "reportedEPS": "-0.1", "estimatedEPS": "-0.55", "surprise": "0.45", "surprisePercentage": "81.8182"}, {"fiscalDateEnding": "2016-09-30", "reportedDate": "2016-11-14", "reportedEPS": "-0.55", "estimatedEPS": "-0.2", "surprise": "-0.35", "surprisePercentage": "-175"}, {"fiscalDateEnding": "2016-06-30", "reportedDate": "2016-07-29", "reportedEPS": "-0.3316", "estimatedEPS": "None", "surprise": "None", "surprisePercentage": "None"}, {"fiscalDateEnding": "2016-03-31", "reportedDate": "2016-04-29", "reportedEPS": "-0.23", "estimatedEPS": "-0.05", "surprise": "-0.18", "surprisePercentage": "-360"}, {"fiscalDateEnding": "2015-12-31", "reportedDate": "2016-03-04", "reportedEPS": "-0.69", "estimatedEPS": "-0.11", "surprise": "-0.58", "surprisePercentage": "-527.2727"}, {"fiscalDateEnding": "2015-09-30", "reportedDate": "2015-11-16", "reportedEPS": "-0.7741", "estimatedEPS": "None", "surprise": "None", "surprisePercentage": "None"}, {"fiscalDateEnding": "2015-06-30", "reportedDate": "2015-08-14", "reportedEPS": "-2.2574", "estimatedEPS": "None", "surprise": "None", "surprisePercentage": "None"}, {"fiscalDateEnding": "2015-03-31", "reportedDate": "2015-05-15", "reportedEPS": "-0.9248", "estimatedEPS": "None", "surprise": "None", "surprisePercentage": "None"}, {"fiscalDateEnding": "2014-12-31", "reportedDate": "2015-03-31", "reportedEPS": "-0.7558", "estimatedEPS": "None", "surprise": "None", "surprisePercentage": "None"}, {"fiscalDateEnding": "2014-09-30", "reportedDate": "2014-09-30", "reportedEPS": "-6.87", "estimatedEPS": "None", "surprise": "None", "surprisePercentage": "None"}, {"fiscalDateEnding": "2014-06-30", "reportedDate": "2014-06-30", "reportedEPS": "-5.8541", "estimatedEPS": "None", "surprise": "None", "surprisePercentage": "None"}, {"fiscalDateEnding": "2014-03-31", "reportedDate": "2014-03-31", "reportedEPS": "-7.1552", "estimatedEPS": "None", "surprise": "None", "surprisePercentage": "None"}, {"fiscalDateEnding": "2013-12-31", "reportedDate": "2013-12-31", "reportedEPS": "-9.7821", "estimatedEPS": "None", "surprise": "None", "surprisePercentage": "None"}, {"fiscalDateEnding": "2013-09-30", "reportedDate": "2013-09-30", "reportedEPS": "-3.9324", "estimatedEPS": "None", "surprise": "None", "surprisePercentage": "None"}, {"fiscalDateEnding": "2013-06-30", "reportedDate": "2013-06-30", "reportedEPS": "0.414", "estimatedEPS": "None", "surprise": "None", "surprisePercentage": "None"}, {"fiscalDateEnding": "2013-03-31", "reportedDate": "2013-03-31", "reportedEPS": "7.1676", "estimatedEPS": "None", "surprise": "None", "surprisePercentage": "None"}, {"fiscalDateEnding": "2012-12-31", "reportedDate": "2012-12-31", "reportedEPS": "14.2188", "estimatedEPS": "None", "surprise": "None", "surprisePercentage": "None"}, {"fiscalDateEnding": "2012-09-30", "reportedDate": "2012-09-30", "reportedEPS": "-23.2799", "estimatedEPS": "None", "surprise": "None", "surprisePercentage": "None"}, {"fiscalDateEnding": "2012-06-30", "reportedDate": "2012-06-30", "reportedEPS": "-29.5905", "estimatedEPS": "None", "surprise": "None", "surprisePercentage": "None"}, {"fiscalDateEnding": "2012-03-31", "reportedDate": "2012-03-31", "reportedEPS": "-32.034", "estimatedEPS": "None", "surprise": "None", "surprisePercentage": "None"}, {"fiscalDateEnding": "2011-12-31", "reportedDate": "2011-12-31", "reportedEPS": "-38.5836", "estimatedEPS": "None", "surprise": "None", "surprisePercentage": "None"}, {"fiscalDateEnding": "2011-09-30", "reportedDate": "2011-09-30", "reportedEPS": "-34.3998", "estimatedEPS": "None", "surprise": "None", "surprisePercentage": "None"}, {"fiscalDateEnding": "2011-06-30", "reportedDate": "2011-06-30", "reportedEPS": "-43.3663", "estimatedEPS": "None", "surprise": "None", "surprisePercentage": "None"}, {"fiscalDateEnding": "2011-03-31", "reportedDate": "2011-03-31", "reportedEPS": "-30.4466", "estimatedEPS": "None", "surprise": "None", "surprisePercentage": "None"}, {"fiscalDateEnding": "2010-12-31", "reportedDate": "2010-12-31", "reportedEPS": "-41.6174", "estimatedEPS": "None", "surprise": "None", "surprisePercentage": "None"}, {"fiscalDateEnding": "2010-09-30", "reportedDate": "2010-09-30", "reportedEPS": "-40.1379", "estimatedEPS": "None", "surprise": "None", "surprisePercentage": "None"}, {"fiscalDateEnding": "2010-06-30", "reportedDate": "2010-06-30", "reportedEPS": "-45.432", "estimatedEPS": "None", "surprise": "None", "surprisePercentage": "None"}, {"fiscalDateEnding": "2010-03-31", "reportedDate": "2010-03-31", "reportedEPS": "-49.3793", "estimatedEPS": "None", "surprise": "None", "surprisePercentage": "None"}, {"fiscalDateEnding": "2009-12-31", "reportedDate": "2009-12-31", "reportedEPS": "-64.8743", "estimatedEPS": "None", "surprise": "None", "surprisePercentage": "None"}, {"fiscalDateEnding": "2009-09-30", "reportedDate": "2009-09-30", "reportedEPS": "-98.4715", "estimatedEPS": "None", "surprise": "None", "surprisePercentage": "None"}, {"fiscalDateEnding": "2009-06-30", "reportedDate": "2009-06-30", "reportedEPS": "-104.8723", "estimatedEPS": "None", "surprise": "None", "surprisePercentage": "None"}, {"fiscalDateEnding": "2009-03-31", "reportedDate": "2009-03-31", "reportedEPS": "-93.0829", "estimatedEPS": "None", "surprise": "None", "surprisePercentage": "None"}, {"fiscalDateEnding": "2008-12-31", "reportedDate": "2008-12-31", "reportedEPS": "-60.6742", "estimatedEPS": "None", "surprise": "None", "surprisePercentage": "None"}, {"fiscalDateEnding": "2008-09-30", "reportedDate": "2008-09-30", "reportedEPS": "-94.3815", "estimatedEPS": "None", "surprise": "None", "surprisePercentage": "None"}]